numeric_converter/__init__.py
numeric_converter/converter.py
numeric_converter-0.1.0.dist-info/licenses/LICENSE
numeric_converter-0.1.0.dist-info/METADATA
numeric_converter-0.1.0.dist-info/WHEEL
numeric_converter-0.1.0.dist-info/top_level.txt
numeric_converter-0.1.0.dist-info/RECORD
